pyre_tui/__init__.py
pyre_tui/cli.py
pyre_tui/highlighters/__init__.py
pyre_tui/highlighters/pattern_highlight.py
pyre_tui/logic/Debouncer.py
pyre_tui/logic/GlobalState.py
pyre_tui/logic/RegexLogic.py
pyre_tui/logic/__init__.py
pyre_tui/metaclasses/__init__.py
pyre_tui/metaclasses/singelton.py
pyre_tui/pyre.py
pyre_tui/pyre.tcss
pyre_tui/screens/Help/Help.py
pyre_tui/screens/Help/HelpScreen.tcss
pyre_tui/screens/Help/__init__.py
pyre_tui/screens/Home/Home.py
pyre_tui/screens/Home/Home.tcss
pyre_tui/screens/Home/__init__.py
pyre_tui/screens/RegexModes/RegexModes.py
pyre_tui/screens/RegexModes/RegexModes.tcss
pyre_tui/screens/RegexModes/__init__.py
pyre_tui/screens/RegexOptions/RegexOptions.py
pyre_tui/screens/RegexOptions/RegexOptions.tcss
pyre_tui/screens/RegexOptions/__init__.py
pyre_tui/screens/__init__.py
pyre_tui/tmp_pyre.py
pyre_tui/widgets/__init__.py
pyre_tui/widgets/inputs/CmdInput/CmdInput.py
pyre_tui/widgets/inputs/CmdInput/__init__.py
pyre_tui/widgets/inputs/ColoredInputArea/ColoredInputArea.py
pyre_tui/widgets/inputs/ColoredInputArea/__init__.py
pyre_tui/widgets/inputs/PatternInput/PatternInput.py
pyre_tui/widgets/inputs/PatternInput/__init__.py
pyre_tui/widgets/inputs/SubstitutionInput/SubstitutionInput.py
pyre_tui/widgets/inputs/SubstitutionInput/__init__.py
pyre_tui/widgets/inputs/SubstitutionInputArea/SubstitutionInputArea.py
pyre_tui/widgets/inputs/SubstitutionInputArea/__init__.py
pyre_tui/widgets/inputs/__init__.py
pyre_tui/widgets/labels/Logo/Logo.py
pyre_tui/widgets/labels/Logo/__init__.py
pyre_tui/widgets/labels/__init__.py
pyre_tui/widgets/widgets/CustomHeader/CustomHeader.py
pyre_tui/widgets/widgets/CustomHeader/__init__.py
pyre_tui/widgets/widgets/FooterMode/FooterMode.py
pyre_tui/widgets/widgets/FooterMode/__init__.py
pyre_tui/widgets/widgets/FooterOptions/FooterOptions.py
pyre_tui/widgets/widgets/FooterOptions/__init__.py
pyre_tui/widgets/widgets/GeneralData/GeneralData.py
pyre_tui/widgets/widgets/GeneralData/__init__.py
pyre_tui-0.1.15.dist-info/LICENSE
pyre_tui-0.1.15.dist-info/METADATA
pyre_tui-0.1.15.dist-info/WHEEL
pyre_tui-0.1.15.dist-info/entry_points.txt
pyre_tui-0.1.15.dist-info/RECORD
