Metadata-Version: 2.3
Name: pyre_tui
Version: 0.1.15
Summary: 
Home-page: https://github.com/dor1202/pyre
Author: Dor Schrieber
Author-email: schreiberdor@gmail.com
Requires-Python: >=3.11,<4.0
Classifier: License :: OSI Approved :: MIT License
Classifier: Programming Language :: Python :: 3
Classifier: Programming Language :: Python :: 3.11
Classifier: Programming Language :: Python :: 3.12
Classifier: Programming Language :: Python :: 3.13
Classifier: Programming Language :: Python :: 3.10
Classifier: Programming Language :: Python :: 3.8
Classifier: Programming Language :: Python :: 3.9
Requires-Dist: colorama (>=0.4.4,<0.5.0)
Requires-Dist: rich (>=13.9.4,<14.0.0)
Requires-Dist: textual (>=1.0.0,<2.0.0)
Requires-Dist: typer (>=0.9.0,<0.10.0)
Project-URL: Repository, https://github.com/dor1202/pyre
